<?xml version="1.0" encoding="utf-8"?>
<resources>
    <en>
        <toturial name="big_buck_bunny_720p_1mb" url="https://www.sample-videos.com/video/mp4/720/big_buck_bunny_720p_1mb.mp4"/>
        <toturial name="big_buck_bunny_720p_2mb" url="https://www.sample-videos.com/video/mp4/720/big_buck_bunny_720p_2mb.mp4"/>
        <toturial name="big_buck_bunny_720p_5mb" url="https://www.sample-videos.com/video/mp4/720/big_buck_bunny_720p_5mb.mp4"/>
        <toturial name="big_buck_bunny_720p_10mb" url="https://www.sample-videos.com/video/mp4/720/big_buck_bunny_720p_10mb.mp4"/>
        <toturial name="big_buck_bunny_720p_1mb" url="https://www.sample-videos.com/video/mp4/720/big_buck_bunny_720p_1mb.mp4"/>
        <toturial name="big_buck_bunny_720p_2mb" url="https://www.sample-videos.com/video/mp4/720/big_buck_bunny_720p_2mb.mp4"/>
        <toturial name="big_buck_bunny_720p_5mb" url="https://www.sample-videos.com/video/mp4/720/big_buck_bunny_720p_5mb.mp4"/>
        <toturial name="big_buck_bunny_720p_10mb" url="https://www.sample-videos.com/video/mp4/720/big_buck_bunny_720p_10mb.mp4"/>
    </en>
</resources>
